topsis/__init__.py
topsis/topsis.py
topsis_arush_102303889-1.0.1.dist-info/licenses/LICENCE
topsis_arush_102303889-1.0.1.dist-info/METADATA
topsis_arush_102303889-1.0.1.dist-info/WHEEL
topsis_arush_102303889-1.0.1.dist-info/entry_points.txt
topsis_arush_102303889-1.0.1.dist-info/top_level.txt
topsis_arush_102303889-1.0.1.dist-info/RECORD
